qualdocs/__init__.py
qualdocs/core.py
qualdocs/get_credentials.py
qualdocs-0.1.1.dist-info/LICENSE
qualdocs-0.1.1.dist-info/METADATA
qualdocs-0.1.1.dist-info/WHEEL
qualdocs-0.1.1.dist-info/top_level.txt
qualdocs-0.1.1.dist-info/RECORD
